smartg4f/__init__.py
smartg4f/core.py
smartg4f-1.2.dist-info/METADATA
smartg4f-1.2.dist-info/WHEEL
smartg4f-1.2.dist-info/top_level.txt
smartg4f-1.2.dist-info/RECORD
