Metadata-Version: 2.1
Name: smartg4f
Version: 1.2
Summary: Smart g4f provider selector
Home-page: https://github.com/grandguyjs/smartg4f
Author: GrandguyJS
Author-email: grandguymc@gmail.com
Classifier: Programming Language :: Python :: 3
Classifier: License :: OSI Approved :: MIT License
Classifier: Operating System :: OS Independent
Requires-Python: >=3.6
Requires-Dist: g4f
